girder_ldap/__init__.py
girder_ldap/settings.py
girder_ldap/web_client/dist/girder-plugin-ldap.umd.cjs
girder_ldap/web_client/dist/style.css
girder_ldap-5.0.0a14.dev27.dist-info/METADATA
girder_ldap-5.0.0a14.dev27.dist-info/WHEEL
girder_ldap-5.0.0a14.dev27.dist-info/entry_points.txt
girder_ldap-5.0.0a14.dev27.dist-info/top_level.txt
girder_ldap-5.0.0a14.dev27.dist-info/RECORD
